tradex_common_python/__init__.py
tradex_common_python/async_lib/BlockingIO.py
tradex_common_python/async_lib/TaskQueue.py
tradex_common_python/async_lib/__init__.py
tradex_common_python/errors/FieldLengthError.py
tradex_common_python/errors/FieldRequireError.py
tradex_common_python/errors/GeneralError.py
tradex_common_python/errors/InvalidParameterError.py
tradex_common_python/errors/InvalidValueError.py
tradex_common_python/errors/UriNotFoundError.py
tradex_common_python/errors/__init__.py
tradex_common_python/errors/codes.py
tradex_common_python/kafka/Consumer.py
tradex_common_python/kafka/Message.py
tradex_common_python/kafka/Producer.py
tradex_common_python/kafka/RequestHandler.py
tradex_common_python/kafka/__init__.py
tradex_common_python/models/Base.py
tradex_common_python/models/Constants.py
tradex_common_python/models/Request.py
tradex_common_python/models/RequestTest.py
tradex_common_python/models/Response.py
tradex_common_python/models/__init__.py
tradex_common_python/models/tux_broadcast/__init__.py
tradex_common_python/models/tux_broadcast/vcsc/DrMatchingOrderNotify.py
tradex_common_python/models/tux_broadcast/vcsc/MatchingOrderNotify.py
tradex_common_python/models/tux_broadcast/vcsc/SocketClusterNotify.py
tradex_common_python/models/tux_broadcast/vcsc/UserLoginNotification.py
tradex_common_python/models/tux_broadcast/vcsc/UserLogoutNotification.py
tradex_common_python/models/tux_broadcast/vcsc/__init__.py
tradex_common_python/models/tuxedo/Authen.py
tradex_common_python/models/tuxedo/__init__.py
tradex_common_python/models/tuxedo/vcsc/AccountAssetInfo.py
tradex_common_python/models/tuxedo/vcsc/AccountBalanceDetails.py
tradex_common_python/models/tuxedo/vcsc/AccountBalanceInfo.py
tradex_common_python/models/tuxedo/vcsc/AccountBuyAble.py
tradex_common_python/models/tuxedo/vcsc/AccountCashBalance.py
tradex_common_python/models/tuxedo/vcsc/AccountChangeHTSPassword.py
tradex_common_python-0.1.dist-info/DESCRIPTION.rst
tradex_common_python-0.1.dist-info/METADATA
tradex_common_python-0.1.dist-info/RECORD
tradex_common_python-0.1.dist-info/WHEEL
tradex_common_python-0.1.dist-info/metadata.json
tradex_common_python-0.1.dist-info/top_level.txt
