Metadata-Version: 2.0
Name: tradex-common-python
Version: 0.1
Summary: common for tradex project using python language
Home-page: UNKNOWN
Author: HiepNtt
Author-email: tuanhiep1232@gmail.com
License: UNKNOWN
Platform: UNKNOWN
Classifier: Programming Language :: Python :: 3
Classifier: License :: OSI Approved :: MIT License
Classifier: Operating System :: OS Independent
Requires-Dist: confluent-kafka
Requires-Dist: simplejson
